<?xml version="1.0" encoding="UTF-8"?>
  <?xml-stylesheet type="text/xsl" href="rfc2629.xslt" ?>
  <!-- generated by https://github.com/cabo/kramdown-rfc version 1.6.33 (Ruby 2.6.10) -->


<!DOCTYPE rfc  [
  <!ENTITY nbsp    "&#160;">
  <!ENTITY zwsp   "&#8203;">
  <!ENTITY nbhy   "&#8209;">
  <!ENTITY wj     "&#8288;">

]>


<rfc ipr="trust200902" docName="draft-horley-v6ops-lab-03" category="std" consensus="true" submissionType="IETF" tocInclude="true" sortRefs="true" symRefs="true">
  <front>
    <title abbrev="Expanding the IPv6 Lab Use Space">Expanding the IPv6 Lab Use Space</title>

    <author initials="N." surname="Buraglio" fullname="Nick Buraglio">
      <organization>Energy Sciences Network</organization>
      <address>
        <email>buraglio@forwardingplane.net</email>
      </address>
    </author>
    <author initials="C." surname="Cummings" fullname="Chris Cummings">
      <organization>Energy Sciences Network</organization>
      <address>
        <email>chriscummings@es.net</email>
      </address>
    </author>
    <author initials="" surname="Kevin Myers">
      <organization>IP ArchiTechs</organization>
      <address>
        <email>kevin.myers@iparchitechs.com</email>
      </address>
    </author>
    <author initials="" surname="Russ White">
      <organization>Juniper Networks</organization>
      <address>
        <email>russ@riw.us</email>
      </address>
    </author>
    <author initials="E." surname="Horley" fullname="Ed Horley">
      <organization>Hexabuild</organization>
      <address>
        <email>ed@hexabuild.io</email>
      </address>
    </author>
    <author initials="T." surname="Coffeen" fullname="Tom Coffeen">
      <organization>Hexabuild</organization>
      <address>
        <email>tom@hexabuild.io</email>
      </address>
    </author>
    <author initials="S." surname="Hogg" fullname="Scott Hogg">
      <organization>Hexabuild</organization>
      <address>
        <email>scott@hexabuild.io</email>
      </address>
    </author>

    <date year="2023" month="July" day="10"/>

    <area>Int</area>
    <workgroup>V6OPS</workgroup>
    <keyword>Internet-Draft</keyword>

    <abstract>


<?line 64?>

<t>To reduce the likelihood of addressing conflicts and confusion between lab deployments and non-lab (i.e., production) deployments, an IPv6 unicast address prefix is reserved for use in lab, proof-of-concept, and validation networks as well as for any similar use case. This document describes the use of the IPv6 address prefix 0200::/7 as a prefix reserved for this purpose (repurposing the deprecated OSI NSAP-mapped prefix).</t>



    </abstract>



  </front>

  <middle>


<?line 68?>

<section anchor="introduction"><name>Introduction</name>

<t>The address architecture for IPv6 <xref target="RFC4291"/> does not explicitly define any prefixes allocated exclusively for lab use, nor is such address space allocated in <xref target="RFC6890"/> or in <xref target="RFC8200"/>. While lab deployments could potentially use IPv6 address prefixes typically assigned and configured in non-lab network, the use of such addressing in lab environments may create addressing conflicts and unnecessary operational confusion. For instance, designing labs utilizing ULA fc00::/7 <xref target="RFC4193"/> is problematic due to the random global ID requirement preventing hierarchical network prefix design possibilities. Further, default address selection behavior <xref target="RFC6724"/> by end nodes may result in a de-preference of such addresses and prevent lab deployments from accurately modeling their desired non-lab equivalents, especially in the testing of devices that are incapable of adjusting the global source selection table.
To resolve these problems involved in building large-scale lab networks, and pre-staging, or automating large-scale networks for deployment, this document allocates the IPv6 address prefix 0200::/7 for these purposes.
The goal is to allow organization to share working lab configuration files (with little or no need of modification) to be deployed in a third party lab environment, public and private clouds, virtualization or hosting environments as well as in other networks such as Service Providers, Enterprise, Government, IoT, and Energy, all with the knowledge that the lab GUA address space will perform the same as any GUA but with the added knowledge that filtering will be used to protect accidental leaks to the Internet. 
The following criteria is for selecting the lab prefix:</t>

<t><list style="symbols">
  <t>Address space should reside outside of IANA allocated GUA block of 2000::/3</t>
  <t>The precedence for the lab prefix should not be lower than the GUA prefix as defined in <xref target="RFC6724"/> (unlike ULA).</t>
  <t>Reduce the operational impacts to IANA and the RIR's in selecting lab prefix space.</t>
</list></t>

</section>
<section anchor="terminology"><name>Terminology</name>

<t>The key words "<bcp14>MUST</bcp14>", "<bcp14>MUST NOT</bcp14>", "<bcp14>REQUIRED</bcp14>", "<bcp14>SHALL</bcp14>", "<bcp14>SHALL
NOT</bcp14>", "<bcp14>SHOULD</bcp14>", "<bcp14>SHOULD NOT</bcp14>", "<bcp14>RECOMMENDED</bcp14>", "<bcp14>NOT RECOMMENDED</bcp14>",
"<bcp14>MAY</bcp14>", and "<bcp14>OPTIONAL</bcp14>" in this document are to be interpreted as
described in BCP 14 <xref target="RFC2119"/> <xref target="RFC8174"/> when, and only when, they
appear in all capitals, as shown here.</t>

<?line -18?>

</section>
<section anchor="assignment-of-address-space-for-use-in-large-scale-lab-and-prototyping-environments"><name>Assignment of address space for use in large-scale lab and prototyping environments</name>

<t>The prefix reserved for large scale lab and testing purposes is 0200::/7.</t>

<section anchor="operational-implications"><name>Operational Implications</name>

<t>This space <bcp14>SHOULD NOT</bcp14> be employed for addressing use cases which are already defined in other RFCs, such as addresses set apart for documentation, testing, etc.
Enterprise and large-scale networks have some specific criteria around building and validating prior to deployment. The issues with ULA for infrastructure modeling, lab creation, configuration and behavior testing at the host level are notably impactful in large enterprises as well as continental and global scale networks. This is primarily, but not exclusively, due to the increased focus on large-scale hosts, servers, and application testing. Additionally, it is likely that both GUA and ULA may co-exist or are planned to co-exist, and reconfiguring lab hosts, network elements, operational technology systems, and IoT hardware isn't practical or desirable due to inconsistent results for host preference due to <xref target="RFC6724"/> behavior.
Most large-scale enterprises strive to build lab, dev, and QA environments that reflect production as accurately as possible. This is a fairly straightforward way to avoid disparity between production and non-production. Enterprise environments are an area that need increased IPv6 adoption. In an effort to enable a more approachable mechanism to model a global scale network,  and to avoid the pitfalls of ULA de-preferenced host behavior or mis-use (i.e. address space squatting) on other IPv6 space, a specific IPv6 lab prefix is being assigned.</t>

<section anchor="resource-utilization"><name>Resource utilization</name>

<t>The prefix in question, (0200::/7) has previously been used for the OSI NSAP-mapped prefix set in <xref target="RFC4048"/> and <xref target="RFC4548"/>, and deprecated, this address prefix is already limited in its usability and has not been officially re-purposed. The address prefix was returned to IANA and is available to be marked for other purposes.
This assignment implies that IPv6 network operators <bcp14>SHOULD</bcp14> add this address prefix to the list of non-routable IPv6 address space, and if packet filters are deployed, then this address prefix <bcp14>SHOULD</bcp14> be added to packet filters. This is not a local-use address prefix so these filters may be used in both local and public contexts.</t>

<t>As noted <eref target="https://www.iana.org/assignments/ipv6-address-space/ipv6-address-space.xhtml">here</eref> by the IANA Internet Protocol Version 6 Address Space allocation reference, 0200::/7 was deprecated as of December 2004 by <xref target="RFC4048"/>. This space is outside of the 2000::/3 address block, making it significantly easier to filter and providing straightforward visual and programmatic identification. Because the resource has been previously allocated, no new resources are required. Additionally, as noted by the IANA allocation list, approximately 85% of the IPv6 address space is reserved for future
definition and use, and is not assigned by IANA at this time, leaving ample room for growth over the coming decades.</t>

</section>
</section>
</section>
<section anchor="acknowledgements"><name>Acknowledgements</name>

<t>The authors would like to acknowledge the valuable input and contributions of the v6ops WG. The authors further acknowledge the work of Bob Hinden and Stephen Deering, in authoring the protocol standard and the addressing architecture for IPv6.</t>

</section>
<section anchor="security-considerations"><name>Security Considerations</name>

<t>The addresses assigned for lab and staging use <bcp14>SHOULD</bcp14> be filtered as noted above.
Setting aside address space for lab and staging use, and adding this address space to common filters to prevent destinations in this space from being routed in production networks (including the global Internet) improves security by preventing the leakage of prefixes used for testing into production environments. As such, setting aside this space improves the overall security posture of the Internet.</t>

</section>
<section anchor="iana-considerations"><name>IANA Considerations</name>

<t>IANA to allocate and record the reservation of the IPv6 global unicast address prefix 0200::/7 as a lab-only prefix in the IPv6 address registry. No end party is to be assigned this address.</t>

</section>
<section anchor="appendix-a"><name>Appendix A.</name>

</section>


  </middle>

  <back>


    <references title='Normative References'>



<reference anchor='RFC2119'>
  <front>
    <title>Key words for use in RFCs to Indicate Requirement Levels</title>
    <author fullname='S. Bradner' initials='S.' surname='Bradner'/>
    <date month='March' year='1997'/>
    <abstract>
      <t>In many standards track documents several words are used to signify the requirements in the specification. These words are often capitalized. This document defines these words as they should be interpreted in IETF documents. This document specifies an Internet Best Current Practices for the Internet Community, and requests discussion and suggestions for improvements.</t>
    </abstract>
  </front>
  <seriesInfo name='BCP' value='14'/>
  <seriesInfo name='RFC' value='2119'/>
  <seriesInfo name='DOI' value='10.17487/RFC2119'/>
</reference>

<reference anchor='RFC8200'>
  <front>
    <title>Internet Protocol, Version 6 (IPv6) Specification</title>
    <author fullname='S. Deering' initials='S.' surname='Deering'/>
    <author fullname='R. Hinden' initials='R.' surname='Hinden'/>
    <date month='July' year='2017'/>
    <abstract>
      <t>This document specifies version 6 of the Internet Protocol (IPv6). It obsoletes RFC 2460.</t>
    </abstract>
  </front>
  <seriesInfo name='STD' value='86'/>
  <seriesInfo name='RFC' value='8200'/>
  <seriesInfo name='DOI' value='10.17487/RFC8200'/>
</reference>

<reference anchor='RFC8174'>
  <front>
    <title>Ambiguity of Uppercase vs Lowercase in RFC 2119 Key Words</title>
    <author fullname='B. Leiba' initials='B.' surname='Leiba'/>
    <date month='May' year='2017'/>
    <abstract>
      <t>RFC 2119 specifies common key words that may be used in protocol specifications. This document aims to reduce the ambiguity by clarifying that only UPPERCASE usage of the key words have the defined special meanings.</t>
    </abstract>
  </front>
  <seriesInfo name='BCP' value='14'/>
  <seriesInfo name='RFC' value='8174'/>
  <seriesInfo name='DOI' value='10.17487/RFC8174'/>
</reference>




    </references>

    <references title='Informative References'>



<reference anchor='RFC6724'>
  <front>
    <title>Default Address Selection for Internet Protocol Version 6 (IPv6)</title>
    <author fullname='D. Thaler' initials='D.' role='editor' surname='Thaler'/>
    <author fullname='R. Draves' initials='R.' surname='Draves'/>
    <author fullname='A. Matsumoto' initials='A.' surname='Matsumoto'/>
    <author fullname='T. Chown' initials='T.' surname='Chown'/>
    <date month='September' year='2012'/>
    <abstract>
      <t>This document describes two algorithms, one for source address selection and one for destination address selection. The algorithms specify default behavior for all Internet Protocol version 6 (IPv6) implementations. They do not override choices made by applications or upper-layer protocols, nor do they preclude the development of more advanced mechanisms for address selection. The two algorithms share a common context, including an optional mechanism for allowing administrators to provide policy that can override the default behavior. In dual-stack implementations, the destination address selection algorithm can consider both IPv4 and IPv6 addresses -- depending on the available source addresses, the algorithm might prefer IPv6 addresses over IPv4 addresses, or vice versa.</t>
      <t>Default address selection as defined in this specification applies to all IPv6 nodes, including both hosts and routers. This document obsoletes RFC 3484. [STANDARDS-TRACK]</t>
    </abstract>
  </front>
  <seriesInfo name='RFC' value='6724'/>
  <seriesInfo name='DOI' value='10.17487/RFC6724'/>
</reference>

<reference anchor='RFC4048'>
  <front>
    <title>RFC 1888 Is Obsolete</title>
    <author fullname='B. Carpenter' initials='B.' surname='Carpenter'/>
    <date month='April' year='2005'/>
    <abstract>
      <t>This document recommends that RFC 1888, on Open Systems Interconnection (OSI) Network Service Access Points (NSAPs) and IPv6, be reclassified as Historic, as most of it has no further value, apart from one section, which is faulty. This memo provides information for the Internet community.</t>
    </abstract>
  </front>
  <seriesInfo name='RFC' value='4048'/>
  <seriesInfo name='DOI' value='10.17487/RFC4048'/>
</reference>

<reference anchor='RFC4193'>
  <front>
    <title>Unique Local IPv6 Unicast Addresses</title>
    <author fullname='R. Hinden' initials='R.' surname='Hinden'/>
    <author fullname='B. Haberman' initials='B.' surname='Haberman'/>
    <date month='October' year='2005'/>
    <abstract>
      <t>This document defines an IPv6 unicast address format that is globally unique and is intended for local communications, usually inside of a site. These addresses are not expected to be routable on the global Internet. [STANDARDS-TRACK]</t>
    </abstract>
  </front>
  <seriesInfo name='RFC' value='4193'/>
  <seriesInfo name='DOI' value='10.17487/RFC4193'/>
</reference>

<reference anchor='RFC4291'>
  <front>
    <title>IP Version 6 Addressing Architecture</title>
    <author fullname='R. Hinden' initials='R.' surname='Hinden'/>
    <author fullname='S. Deering' initials='S.' surname='Deering'/>
    <date month='February' year='2006'/>
    <abstract>
      <t>This specification defines the addressing architecture of the IP Version 6 (IPv6) protocol. The document includes the IPv6 addressing model, text representations of IPv6 addresses, definition of IPv6 unicast addresses, anycast addresses, and multicast addresses, and an IPv6 node's required addresses.</t>
      <t>This document obsoletes RFC 3513, "IP Version 6 Addressing Architecture". [STANDARDS-TRACK]</t>
    </abstract>
  </front>
  <seriesInfo name='RFC' value='4291'/>
  <seriesInfo name='DOI' value='10.17487/RFC4291'/>
</reference>

<reference anchor='RFC4548'>
  <front>
    <title>Internet Code Point (ICP) Assignments for NSAP Addresses</title>
    <author fullname='E. Gray' initials='E.' surname='Gray'/>
    <author fullname='J. Rutemiller' initials='J.' surname='Rutemiller'/>
    <author fullname='G. Swallow' initials='G.' surname='Swallow'/>
    <date month='May' year='2006'/>
    <abstract>
      <t>This document is intended to accomplish two highly inter-related tasks: to establish an "initial" Internet Code Point (ICP) assignment for each of IPv4 and IPv6 address encoding in Network Service Access Point (NSAP) Addresses, and to recommend an IANA assignment policy for currently unassigned ICP values. In the first task, this document is a partial replacement for RFC 1888 -- particularly for section 6 of RFC 1888. In the second task, this document incorporates wording and specifications from ITU-T Recommendation X.213 and further recommends that IANA use the "IETF consensus" assignment policy in making future ICP assignments. [STANDARDS-TRACK]</t>
    </abstract>
  </front>
  <seriesInfo name='RFC' value='4548'/>
  <seriesInfo name='DOI' value='10.17487/RFC4548'/>
</reference>

<reference anchor='RFC6890'>
  <front>
    <title>Special-Purpose IP Address Registries</title>
    <author fullname='M. Cotton' initials='M.' surname='Cotton'/>
    <author fullname='L. Vegoda' initials='L.' surname='Vegoda'/>
    <author fullname='R. Bonica' initials='R.' role='editor' surname='Bonica'/>
    <author fullname='B. Haberman' initials='B.' surname='Haberman'/>
    <date month='April' year='2013'/>
    <abstract>
      <t>This memo reiterates the assignment of an IPv4 address block (192.0.0.0/24) to IANA. It also instructs IANA to restructure its IPv4 and IPv6 Special-Purpose Address Registries. Upon restructuring, the aforementioned registries will record all special-purpose address blocks, maintaining a common set of information regarding each address block.</t>
    </abstract>
  </front>
  <seriesInfo name='BCP' value='153'/>
  <seriesInfo name='RFC' value='6890'/>
  <seriesInfo name='DOI' value='10.17487/RFC6890'/>
</reference>




    </references>



  </back>

<!-- ##markdown-source:
H4sIAItmrGQAA5VZbXPbNhL+zl+BS+emSUdi4iR1E0+njZI4je8S27Wcdjqd
foBISMKZJBQAlKx28l/ut9wvu2cXAEnJSq+XyYz5AmIX+/Lss6vxeJx57St1
Ik5vV7IpdbMQfqnE2eX6WLyTM/HBKTFdyUJlcjazav0XFpamaGSNLUsr5368
NLZS2/H62KzcuJKz8aMnGbZ5krl2VmvntGn8doXlZ6fXb7JC+hPhfJnplT0R
3rbOP3706Pmjx5m0SmJR47PN4kT8dHxxOc1uNvxE2Ub58WsSl2WZbD1knmSC
/43jXyF0407EeS5etlYuKm26F0Hbc13c3H1nLISdNsoutmJaaNUUyolz5TfG
3nSLVC11dSJm8eMXc2M30pKNVpVsVA7tDmvzKhev2rrGQrenzaul1e7uy/9H
nYK2KOIOL5T7vBr/VGvdiPdbZfcknV2KiS2W+loVS7e//w19ldf01Qu9krTO
07q8MPW+HBZz1TonfqZV2VDIP9pGr5RNx+jkRDEIAffC6k3eusPan+biLcfY
nglPy/3nLO6tupWzVlfl/nlU+WKZ3uVdCOwJu4bHzHyuVLMn7drUd978uTxv
6r8gcEqnWyz2pE0L4/3uiz8X5uiDXXFZY2wtvV4rypWrN68eHx09j5fPkHQn
+DrLdDPfW3b8zeOn8fLpo6fP0uXR8ycHLh8/P0qXX3drj589f4TLjPYfj8dC
zpy3skDyXhthVdkWisGl0jeq0ktjSmHmQpalVcALIE9hmnmlC+8EoIjvWsIR
MUMIwQECMCNKtarMtlZNXNWYhuBH3Ne5ykdiZQ3keHz1YLh0hLUB1BCVhXQ+
icUHaq5vBbISt8quVSlgGdEC9zRL5D3NfIz/0KhQKz9iwWtZ6VKSJNHEEBfS
iY2qKvpLm8hmK5yudSXDhhCscnG9hDCgaUuaQUlXWD1DvpNpaBVs0kHwnpaP
yH8nD78hATI93NHb0+ar1q4MdrpvVbhMsA6LWAUsxuKL6Zk4n04ux7VcrXAf
NnuQB9fVuiwrlWVfEA53JoUjsUnSKUGDb61i2azxH3/E+Pj0CYfEsRrjhbpd
wa+oSFuoMNeNYtMEkVgiq8oErdRtUcHna4WVtCV5FjYZYRdLPnJtsewUcFSX
Bh/DXyyd4hDS6Yv4hOL+06ecUKpSd8KoMG0FAxiPO43ttuyGA/YnJ21XiB9a
IxGziwZiU6zqBQzBWqSYjHExGrp2eAJySwgyoZq1tqYJCtVyKwrURa8+nx1t
0yhUCSftVhjgLEeirPqsycUbtoDzElE7okCDvrQR5DnRel3p3+n2w7uJmBcx
sIL7kOkwIEWSNbNKEU4UomyRvobPYqEBgHFRmRlEnr1GDH5stVUc0bDVmiyJ
rZcailGYwGTJGilsgz4wO043gy5eo5aJN62FAEvqzmVb9XnqVKU4CIEGS7nW
OFtwNmALus62MCGhAbZl++Ej+hzmldhrTEKVpcK67wQV7Bm1vhMcc4uDyqIA
CfAUlTUkVDGftOVTkNeTy8kOQIaAOcqtVBEiCnqQ4bxybBjoUKLOFpz2Eqe0
BDeFXEmYO6Div9qwlD6LhnamtThAbwpPy/MAr85Ua8ZXxFl0m8Oea3rMUckV
IvjfLtTYwSchFxJ8jZIhxoiZBVaOKIfAuwwFwN6HHeZRmvYGGwUE6uAtZaf7
35gW4IvVD/jlcsabhcHRsSdij3bbUEmUjf49YC+euiWZj7SJ0d2lY1gyR9I7
cX+j/RK1x3uysIXHcAbFJQg+1XPEaCgb2HGm4pGC5SQdysI00vrtfrqiPrQz
5GU0HryPtC0q05YwKFb5FoUiKguxSxPcupPwg7oBcYYyoDdwCFYnpkB5RIy4
tGatS9CzESgjSDJkEkL+YNYgzEGjM3MdnBk45YgMJ/j85IWbxmwqVS5UiD0u
yTjTDx8me9C60fgM2EJUgZc5sBSuPUBvWj5rfb8tvoW59jaH7aEiHZg3mzEO
lmRjxCgVD8otnKbxcHKl5I1LGJMagFxwFMwN+Z5x0GraUlJMUMzEdIipQicJ
kXWSZV+Jyc6B3JKhHk8gUpjWh79zcTY5nwwqCZ8NNzf0DvFJAfoEu5EiVEFV
yUgSI3YgM0mgooezQmNFS2TIfto2roMRQyUclK2AZPfbhggSwfIDnP0rcdUz
pyHQ6xpH8myuoD3cTWuuzq6+5DDq7TLUj+yQU2G/VhYthKnMYhvq+o3aUhKV
Ttx7/2F6fW8U/orzC76+Ov3xw9nV6Wu6nr6dvHvXXWRxxfTtxYd3r/ur/stX
F+/fn56/Dh/jqdh5lN17P/nlXgjYexeX12cX55N39wJk7mCJVTE5dYh7Rb6S
Lkscim358tXlf/599BQ2/VskvzBquHl29A1ZeLNUTZBmGkBzuIXpthlRIcm0
gRIGcKwRloSLjhy7aQQSk6z31a9kmd9OxLezYnX09Lv4gA688zDZbOch2+zu
kzsfByMeeHRATGfNned7lt7Vd/LLzn2y++Dht99XRNXGR8++/y6jkJkw5WFf
9MQ9ptYOad6tLwEYjTdEnvahL8TeISrL24jdbVL9TBWCMCAVEIrqL8TFIEXO
aqKdfOdIjk7K9nakaFJ1hHrm7D3hSpQd4AwGs+T4kxV4WbkdJm+Aa4QXAiVh
dc8tnELgUuEIhTLGMus0SscBU/BFnvVozmc9WG1BfWATAxhmboGq1eOhtKbF
d12dH3YpZDNLpAkJ1FfrnBFNO9fSIQnImQwyb5xbtEm2DfQ+sZ5RKK/ETfkA
u4WWBHbsLLkqVhiqewB4MHu2IwAS3GUbUWzeVl3gIDySGXYKI0Rhv1AoSFDi
RDv2id0VM1ddS6srFD+qUqEL6ZqL0ZDNgnjhQI4DoGgdUGHH9qQ5uZYi00aS
BKBIkZUOmlOt0SHySID2pAb3uttQC2eIlFBlsQMZmnm+GatbDdtQ7MEwNFpq
QoVMr4JIlJ1o7ATpUbHEqwH3sdcdlgma3QSUF27rPEhh2A4UAcFkyw1TT9d8
ScQdrmCqbiKxZTYaLQUrIY2gDqV/YNeh/rJnB/w6rt9h5zEo8uw9h8HAukNv
I970OmA8xXDovsGTg8Y/TnaRg20KsVTlBn0/p1/P13EXWoxK9cEhxVxqi7c0
oNCLpY+jPbGBR4hnro0uRamBFkiubTeAGEqJs4f+UT6gY3v0joCjoT8yaM3E
sw+7SIvNKmxzRrsLNYdSnrRRDftBIgtpoxVEymLJz2p4F1zY1bSOkxTLDmXG
SAT8TGejuEd1myNWHYE5heNOm1QGv3bpjP+1dmPCRB617MG/+9hKT2nwgNIn
QCIfi1/DgT1e8eMBJYE/ZoqRInbUORUbQPmVig1P6FVlP4JIXzbiY0vZR1B0
P9WBB4hr7i6gd+sq8h5c17puQqI+M/xgrE5sjGZgiFwyWrj/mu5DJPZjlNju
3B0mpTpR6VrH2YRGJLROcq+75X1Iz8AUoaCZwzihWUQHFgtcGRB6b/+NpGkV
gDkCRcf/SPBa6opjI1AlgOBNPHnwyrC5ovV9TddULlNHyl5K0BIAxViXKicU
OnjyiKgVA9qcEwRFidvU3eYvhQUpPUdjVdyo1CyEfEn9FzOz5qCwqMsstR7U
VOxs1Cc8WVkKovcVh/DeTs7EzjNpQMicehVqnQm5+etAZkLDRxVJ3XpYMpuw
CCz+lRjib/eX3q/cycOHm80m17KROXrWh72p3UO9Wh+PoxZjNsaBR/nt0tfV
AxpucEdEbk5tEbWB3hSmEj9BYUKk467ZmQ4HY/Sqy+pR325vuAXp5oGSYeA1
ept6hijBqqckd5AL0Zoh33ExaJ9Iu9QmdbblBmoEU3JbjnLI8yfqsxsaBAL6
tGI+EoyeaCJ6W1q/j8xr7dpkfmsWVtZhKsW9Y9e95+IlzkMe5jFVAhBKtFkA
8A4Vum5vFEYBm255CMA40ir367pMrh56ZWDrKlRsQulbUBAuQs++/vvBsW5n
yx3iO2+Jc2VMMXVXbHgMGpOcwznNH6FH0MGHLPG6xkr00msGVSQ1DmNMzXsv
rNkglmlWwOoUhn5HQiAUsqT5m8hEoPpF18gPeXr4EQ6kjLtc7lOppBTDrl8R
6Ww55XWzAveKA1IUdzAx4uLJFvzjofj5hwhyce95GAHe2TUg0Vy8NDPxVjfw
O+889WpFCPFa8ZxhxN0bb5VGAquUKTQKLSmYUq88IPsHp9ncKE8VyARB9ivi
P2WkVm5nGK5c7480tyYhcZDGrUQPVyHgQ9KFWJIzeCTPpsoHzsyJdbfBOrBt
5KNl/Ol2gJLhM+aRdR3GYIxtPHsJw86SqWs4T9dvR3E09wx1mRA84OCA/3Qd
yX3wmKrtfjlOM+EIUw+oqiCpuROKdpxthzNirhdK3sgFQ0k3ae8Ldmwk0PSb
oQZDioUkDYMy4ulDGw5O1CnCkxQkAPX4nVKoiez6lKZp+sS/gVB67XufH8aZ
ZMGj+kjSbZnABykd536D3I8G+szvULu/8NDv6jyj6AnPHQyxagHEsdtcnBue
gYcpZRiYUm1McTkMDj7WBNynKbHtJI+/2M2Qc9l/AVVFucM+IAAA

-->

</rfc>

